__init__.py
example.py
couchdb_client/__init__.py
couchdb_client/attachment.py
couchdb_client/couchdb.py
couchdb_client/document.py
couchdb_client-1.2.6.dist-info/licenses/LICENSE
docs/conf.py
tests/context.py
tests/test.py
couchdb_client-1.2.6.dist-info/METADATA
couchdb_client-1.2.6.dist-info/WHEEL
couchdb_client-1.2.6.dist-info/top_level.txt
couchdb_client-1.2.6.dist-info/RECORD
