Metadata-Version: 2.4
Name: couchdb_client
Version: 1.2.6
Summary: Very simple CouchDB client
Author-email: Enzo PB <enzo.puiroux@mail.com>
Project-URL: Homepage, https://github.com/EnzoPB/couchdb-client
Project-URL: Issues, https://github.com/EnzoPB/couchdb-client/issues
Classifier: Programming Language :: Python :: 3
Classifier: License :: OSI Approved :: MIT License
Classifier: Operating System :: OS Independent
Requires-Python: >=3.8
License-File: LICENSE
Requires-Dist: requests
Dynamic: license-file
